simpledbstorage/__init__.py
simpledbstorage/models.py
simpledbstorage/storage.py
simpledbstorage/urls.py
simpledbstorage/views.py
simpledbstorage/migrations/0001_initial.py
simpledbstorage/migrations/__init__.py
django_simpledbstorage-0.1.1.dist-info/LICENSE
django_simpledbstorage-0.1.1.dist-info/METADATA
django_simpledbstorage-0.1.1.dist-info/WHEEL
django_simpledbstorage-0.1.1.dist-info/top_level.txt
django_simpledbstorage-0.1.1.dist-info/RECORD
