Metadata-Version: 2.1
Name: django-simpledbstorage
Version: 0.1.1
Summary: A simple Django app to store files in a db.
Home-page: https://github.com/SearchLightNZ/django-simpledbstorage
Author: Nathan Ward
Author-email: nward@serachlight.nz
License: MIT License
Platform: UNKNOWN
Classifier: Environment :: Web Environment
Classifier: Framework :: Django
Classifier: Framework :: Django :: 2.2
Classifier: Intended Audience :: Developers
Classifier: License :: OSI Approved :: BSD License
Classifier: Operating System :: OS Independent
Classifier: Programming Language :: Python
Classifier: Programming Language :: Python :: 3.5
Classifier: Programming Language :: Python :: 3.6
Classifier: Topic :: Internet :: WWW/HTTP
Classifier: Topic :: Internet :: WWW/HTTP :: Dynamic Content
Requires-Dist: python-magic
